{
  "doc_id": "internal_physics_m5_ray_optics_mirrors_lenses",
  "source": "ragaib_internal",
  "source_url": "internal://physics/M5/ray-optics-mirrors-lenses",
  "source_title": "แสงเชิงรังสี กระจก และเลนส์",
  "subject": "physics",
  "grade": "M5",
  "topic": "แสงเชิงรังสี",
  "subtopic": "กระจกและเลนส์",
  "language": "TH",
  "content_type": "lesson",
  "sections": [
    {
      "heading": "สูตรกระจกและเลนส์",
      "text": "แสงเชิงรังสีอธิบายการเดินทางของแสงด้วยเส้นรังสี ใช้มากในการวิเคราะห์กระจกและเลนส์ สูตรสำคัญคือ 1/f = 1/u + 1/v โดย f คือความยาวโฟกัส u คือระยะวัตถุ และ v คือระยะภาพ กำลังขยายใช้ m = v/u หรือ m = ขนาดภาพหารด้วยขนาดวัตถุ กระจกเว้าและเลนส์นูนอาจให้ภาพจริงหรือภาพเสมือนได้ขึ้นกับตำแหน่งวัตถุ ส่วนกระจกนูนและเลนส์เว้ามักให้ภาพเสมือน หัวตั้ง และขนาดเล็กกว่าเดิม จุดที่ควรระวังคือการกำหนดเครื่องหมายของ f, u และ v รวมถึงการบอกชนิดภาพจากแผนภาพรังสี",
      "order": 1
    }
  ],
  "key_terms": ["แสงเชิงรังสี", "กระจก", "เลนส์", "ความยาวโฟกัส", "กำลังขยาย"],
  "equations": ["1/f = 1/u + 1/v", "m = v/u"],
  "examples": [],
  "raw_text": "แสงเชิงรังสีใช้เส้นรังสีเพื่ออธิบายกระจกและเลนส์ สูตรหลักคือ 1/f = 1/u + 1/v และกำลังขยาย m = v/u กระจกเว้าและเลนส์นูนให้ได้ทั้งภาพจริงหรือภาพเสมือน ส่วนกระจกนูนและเลนส์เว้ามักให้ภาพเสมือน หัวตั้ง และเล็กกว่าเดิม",
  "metadata": {
    "scraped_at": "",
    "scraper_version": "internal-v1",
    "content_hash": "internal_physics_m5_ray_optics_mirrors_lenses_v1",
    "normalization_status": "clean"
  }
}
